django_vite_hmr/__init__.py
django_vite_hmr/admin.py
django_vite_hmr/apps.py
django_vite_hmr/models.py
django_vite_hmr/tests.py
django_vite_hmr/views.py
django_vite_hmr/migrations/__init__.py
django_vite_hmr/templatetags/__init__.py
django_vite_hmr/templatetags/vite.py
package/__init__.py
package/admin.py
package/apps.py
package/models.py
package/tests.py
package/views.py
package/migrations/__init__.py
package/templatetags/__init__.py
package/templatetags/vite.py
django_vite_hmr-1.0.3.dist-info/METADATA
django_vite_hmr-1.0.3.dist-info/WHEEL
django_vite_hmr-1.0.3.dist-info/top_level.txt
django_vite_hmr-1.0.3.dist-info/RECORD
